src/__init__.py
src/area_calculator.py
tests/__init__.py
tests/test.py
geometriccalculatelib-1.0.0.dist-info/METADATA
geometriccalculatelib-1.0.0.dist-info/WHEEL
geometriccalculatelib-1.0.0.dist-info/top_level.txt
geometriccalculatelib-1.0.0.dist-info/RECORD
