Metadata-Version: 2.1
Name: geometriccalculatelib
Version: 1.0.0
Summary: A library for geometric calculations
Author: Alexandr M
Author-email: alex.mmdvdvv@gmail.com
